pySpeedDownloader/__init__.py
pySpeedDownloader/pydownloader.py
pySpeedDownloader-0.1.2.dist-info/LICENSE
pySpeedDownloader-0.1.2.dist-info/METADATA
pySpeedDownloader-0.1.2.dist-info/WHEEL
pySpeedDownloader-0.1.2.dist-info/top_level.txt
pySpeedDownloader-0.1.2.dist-info/RECORD
