Metadata-Version: 2.1
Name: pySpeedDownloader
Version: 0.1.2
Summary: A powerful python based downloader module.
Home-page: https://github.com/cuicaihao/py-downloader-app
Author: Chris Cui
Author-email: 
License: UNKNOWN
Platform: UNKNOWN
Classifier: Programming Language :: Python :: 3
Classifier: License :: OSI Approved :: MIT License
Classifier: Operating System :: OS Independent
Requires-Python: >=3.7
Requires-Dist: tqdm (>=4.40.0)
Requires-Dist: requests (>=2.9.1)
Requires-Dist: multitasking (>=0.0.8)
Requires-Dist: retry (>=0.9.1)
